{
  "page": 5,
  "size": 15,
  "totalPages": 10,
  "data": [
    {
      "id": 1,
      "version": 0,
      "name": "AFGHANISTAN",
      "code": "AF"
    },
    {
      "id": 2,
      "version": 0,
      "name": "ALBANIA",
      "code": "AL"
    },
    {
      "id": 3,
      "version": 0,
      "name": "ALGERIA",
      "code": "DZ"
    },
    {
      "id": 4,
      "version": 0,
      "name": "AMERICAN SAMOA",
      "code": "AS"
    },
    {
      "id": 5,
      "version": 0,
      "name": "ANDORRA",
      "code": "AD"
    },
    {
      "id": 6,
      "version": 0,
      "name": "ANGOLA",
      "code": "AO"
    },
    {
      "id": 7,
      "version": 0,
      "name": "ANGUILLA",
      "code": "AI"
    },
    {
      "id": 8,
      "version": 0,
      "name": "ANTARCTICA",
      "code": "AQ"
    },
    {
      "id": 9,
      "version": 0,
      "name": "ANTIGUA AND BARBUDA",
      "code": "AG"
    },
    {
      "id": 10,
      "version": 0,
      "name": "ARGENTINA",
      "code": "AR"
    },
    {
      "id": 11,
      "version": 0,
      "name": "ARMENIA",
      "code": "AM"
    },
    {
      "id": 12,
      "version": 0,
      "name": "ARUBA",
      "code": "AW"
    },
    {
      "id": 13,
      "version": 0,
      "name": "AUSTRALIA",
      "code": "AU"
    },
    {
      "id": 14,
      "version": 0,
      "name": "AUSTRIA",
      "code": "AT"
    },
    {
      "id": 15,
      "version": 0,
      "name": "AZERBAIJAN",
      "code": "AZ"
    },
    {
      "id": 16,
      "version": 0,
      "name": "BAHAMAS",
      "code": "BS"
    },
    {
      "id": 17,
      "version": 0,
      "name": "BAHRAIN",
      "code": "BH"
    },
    {
      "id": 18,
      "version": 0,
      "name": "BANGLADESH",
      "code": "BD"
    },
    {
      "id": 19,
      "version": 0,
      "name": "BARBADOS",
      "code": "BB"
    },
    {
      "id": 20,
      "version": 0,
      "name": "BELARUS",
      "code": "BY"
    },
    {
      "id": 21,
      "version": 0,
      "name": "BELGIUM",
      "code": "BE"
    },
    {
      "id": 22,
      "version": 0,
      "name": "BELIZE",
      "code": "BZ"
    },
    {
      "id": 23,
      "version": 0,
      "name": "BENIN",
      "code": "BJ"
    },
    {
      "id": 24,
      "version": 0,
      "name": "BERMUDA",
      "code": "BM"
    },
    {
      "id": 25,
      "version": 0,
      "name": "BHUTAN",
      "code": "BT"
    },
    {
      "id": 26,
      "version": 0,
      "name": "BOLIVIA",
      "code": "BO"
    },
    {
      "id": 27,
      "version": 0,
      "name": "BOSNIA AND HERZEGOVINA",
      "code": "BA"
    },
    {
      "id": 28,
      "version": 0,
      "name": "BOTSWANA",
      "code": "BW"
    },
    {
      "id": 29,
      "version": 0,
      "name": "BOUVET ISLAND",
      "code": "BV"
    },
    {
      "id": 30,
      "version": 0,
      "name": "BRAZIL",
      "code": "BR"
    },
    {
      "id": 31,
      "version": 0,
      "name": "BRITISH INDIAN OCEAN TERRITORY",
      "code": "IO"
    },
    {
      "id": 32,
      "version": 0,
      "name": "BRUNEI DARUSSALAM",
      "code": "BN"
    },
    {
      "id": 33,
      "version": 0,
      "name": "BULGARIA",
      "code": "BG"
    },
    {
      "id": 34,
      "version": 0,
      "name": "BURKINA FASO",
      "code": "BF"
    },
    {
      "id": 35,
      "version": 0,
      "name": "BURUNDI",
      "code": "BI"
    },
    {
      "id": 36,
      "version": 0,
      "name": "CAMBODIA",
      "code": "KH"
    },
    {
      "id": 37,
      "version": 0,
      "name": "CAMEROON",
      "code": "CM"
    },
    {
      "id": 38,
      "version": 0,
      "name": "CANADA",
      "code": "CA"
    },
    {
      "id": 39,
      "version": 0,
      "name": "CAPE VERDE",
      "code": "CV"
    },
    {
      "id": 40,
      "version": 0,
      "name": "CAYMAN ISLANDS",
      "code": "KY"
    },
    {
      "id": 41,
      "version": 0,
      "name": "CENTRAL AFRICAN REPUBLIC",
      "code": "CF"
    },
    {
      "id": 42,
      "version": 0,
      "name": "CHAD",
      "code": "TD"
    },
    {
      "id": 43,
      "version": 0,
      "name": "CHILE",
      "code": "CL"
    },
    {
      "id": 44,
      "version": 0,
      "name": "CHINA",
      "code": "CN"
    },
    {
      "id": 45,
      "version": 0,
      "name": "CHRISTMAS ISLAND",
      "code": "CX"
    },
    {
      "id": 46,
      "version": 0,
      "name": "COCOS (KEELING) ISLANDS",
      "code": "CC"
    },
    {
      "id": 47,
      "version": 0,
      "name": "COLOMBIA",
      "code": "CO"
    },
    {
      "id": 48,
      "version": 0,
      "name": "COMOROS",
      "code": "KM"
    },
    {
      "id": 49,
      "version": 0,
      "name": "CONGO",
      "code": "CG"
    },
    {
      "id": 50,
      "version": 0,
      "name": "CONGO, THE DEMOCRATIC REPUBLIC OF THE",
      "code": "CD"
    },
    {
      "id": 51,
      "version": 0,
      "name": "COOK ISLANDS",
      "code": "CK"
    },
    {
      "id": 52,
      "version": 0,
      "name": "COSTA RICA",
      "code": "CR"
    },
    {
      "id": 53,
      "version": 0,
      "name": "COTE D'IVOIRE",
      "code": "CI"
    },
    {
      "id": 54,
      "version": 0,
      "name": "CROATIA",
      "code": "HR"
    },
    {
      "id": 55,
      "version": 0,
      "name": "CUBA",
      "code": "CU"
    },
    {
      "id": 56,
      "version": 0,
      "name": "CYPRUS",
      "code": "CY"
    },
    {
      "id": 57,
      "version": 0,
      "name": "CZECH REPUBLIC",
      "code": "CZ"
    },
    {
      "id": 58,
      "version": 0,
      "name": "DENMARK",
      "code": "DK"
    },
    {
      "id": 59,
      "version": 0,
      "name": "DJIBOUTI",
      "code": "DJ"
    },
    {
      "id": 60,
      "version": 0,
      "name": "DOMINICA",
      "code": "DM"
    },
    {
      "id": 61,
      "version": 0,
      "name": "DOMINICAN REPUBLIC",
      "code": "DO"
    },
    {
      "id": 62,
      "version": 0,
      "name": "EAST TIMOR",
      "code": "TP"
    },
    {
      "id": 63,
      "version": 0,
      "name": "ECUADOR",
      "code": "EC"
    },
    {
      "id": 64,
      "version": 0,
      "name": "EGYPT",
      "code": "EG"
    },
    {
      "id": 65,
      "version": 0,
      "name": "EL SALVADOR",
      "code": "SV"
    },
    {
      "id": 66,
      "version": 0,
      "name": "EQUATORIAL GUINEA",
      "code": "GQ"
    },
    {
      "id": 67,
      "version": 0,
      "name": "ERITREA",
      "code": "ER"
    },
    {
      "id": 68,
      "version": 0,
      "name": "ESTONIA",
      "code": "EE"
    },
    {
      "id": 69,
      "version": 0,
      "name": "ETHIOPIA",
      "code": "ET"
    },
    {
      "id": 70,
      "version": 0,
      "name": "FALKLAND ISLANDS (MALVINAS)",
      "code": "FK"
    },
    {
      "id": 71,
      "version": 0,
      "name": "FAROE ISLANDS",
      "code": "FO"
    },
    {
      "id": 72,
      "version": 0,
      "name": "FIJI",
      "code": "FJ"
    },
    {
      "id": 73,
      "version": 0,
      "name": "FINLAND",
      "code": "FI"
    },
    {
      "id": 74,
      "version": 0,
      "name": "FRANCE",
      "code": "FR"
    },
    {
      "id": 75,
      "version": 0,
      "name": "FRENCH GUIANA",
      "code": "GF"
    },
    {
      "id": 76,
      "version": 0,
      "name": "FRENCH POLYNESIA",
      "code": "PF"
    },
    {
      "id": 77,
      "version": 0,
      "name": "FRENCH SOUTHERN TERRITORIES",
      "code": "TF"
    },
    {
      "id": 78,
      "version": 0,
      "name": "GABON",
      "code": "GA"
    },
    {
      "id": 79,
      "version": 0,
      "name": "GAMBIA",
      "code": "GM"
    },
    {
      "id": 80,
      "version": 0,
      "name": "GEORGIA",
      "code": "GE"
    },
    {
      "id": 81,
      "version": 0,
      "name": "GERMANY",
      "code": "DE"
    },
    {
      "id": 82,
      "version": 0,
      "name": "GHANA",
      "code": "GH"
    },
    {
      "id": 83,
      "version": 0,
      "name": "GIBRALTAR",
      "code": "GI"
    },
    {
      "id": 84,
      "version": 0,
      "name": "GREECE",
      "code": "GR"
    },
    {
      "id": 85,
      "version": 0,
      "name": "GREENLAND",
      "code": "GL"
    },
    {
      "id": 86,
      "version": 0,
      "name": "GRENADA",
      "code": "GD"
    },
    {
      "id": 87,
      "version": 0,
      "name": "GUADELOUPE",
      "code": "GP"
    },
    {
      "id": 88,
      "version": 0,
      "name": "GUAM",
      "code": "GU"
    },
    {
      "id": 89,
      "version": 0,
      "name": "GUATEMALA",
      "code": "GT"
    },
    {
      "id": 90,
      "version": 0,
      "name": "GUINEA",
      "code": "GN"
    },
    {
      "id": 91,
      "version": 0,
      "name": "GUINEA-BISSAU",
      "code": "GW"
    },
    {
      "id": 92,
      "version": 0,
      "name": "GUYANA",
      "code": "GY"
    },
    {
      "id": 93,
      "version": 0,
      "name": "HAITI",
      "code": "HT"
    },
    {
      "id": 94,
      "version": 0,
      "name": "HEARD ISLAND AND MCDONALD ISLANDS",
      "code": "HM"
    },
    {
      "id": 95,
      "version": 0,
      "name": "HOLY SEE (VATICAN CITY STATE)",
      "code": "VA"
    },
    {
      "id": 96,
      "version": 0,
      "name": "HONDURAS",
      "code": "HN"
    },
    {
      "id": 97,
      "version": 0,
      "name": "HONG KONG",
      "code": "HK"
    },
    {
      "id": 98,
      "version": 0,
      "name": "HUNGARY",
      "code": "HU"
    },
    {
      "id": 99,
      "version": 0,
      "name": "ICELAND",
      "code": "IS"
    },
    {
      "id": 100,
      "version": 0,
      "name": "INDIA",
      "code": "IN"
    },
    {
      "id": 101,
      "version": 0,
      "name": "INDONESIA",
      "code": "ID"
    },
    {
      "id": 102,
      "version": 0,
      "name": "IRAN, ISLAMIC REPUBLIC OF",
      "code": "IR"
    },
    {
      "id": 103,
      "version": 0,
      "name": "IRAQ",
      "code": "IQ"
    },
    {
      "id": 104,
      "version": 0,
      "name": "IRELAND",
      "code": "IE"
    },
    {
      "id": 105,
      "version": 0,
      "name": "ISRAEL",
      "code": "IL"
    },
    {
      "id": 106,
      "version": 0,
      "name": "ITALY",
      "code": "IT"
    },
    {
      "id": 107,
      "version": 0,
      "name": "JAMAICA",
      "code": "JM"
    },
    {
      "id": 108,
      "version": 0,
      "name": "JAPAN",
      "code": "JP"
    },
    {
      "id": 109,
      "version": 0,
      "name": "JORDAN",
      "code": "JO"
    },
    {
      "id": 110,
      "version": 0,
      "name": "KAZAKSTAN",
      "code": "KZ"
    },
    {
      "id": 111,
      "version": 0,
      "name": "KENYA",
      "code": "KE"
    },
    {
      "id": 112,
      "version": 0,
      "name": "KIRIBATI",
      "code": "KI"
    },
    {
      "id": 113,
      "version": 0,
      "name": "KOREA, DEMOCRATIC PEOPLE'S REPUBLIC OF",
      "code": "KP"
    },
    {
      "id": 114,
      "version": 0,
      "name": "KOREA, REPUBLIC OF",
      "code": "KR"
    },
    {
      "id": 115,
      "version": 0,
      "name": "KOSOVO",
      "code": "KV"
    },
    {
      "id": 116,
      "version": 0,
      "name": "KUWAIT",
      "code": "KW"
    },
    {
      "id": 117,
      "version": 0,
      "name": "KYRGYZSTAN",
      "code": "KG"
    },
    {
      "id": 118,
      "version": 0,
      "name": "LAO PEOPLE'S DEMOCRATIC REPUBLIC",
      "code": "LA"
    },
    {
      "id": 119,
      "version": 0,
      "name": "LATVIA",
      "code": "LV"
    },
    {
      "id": 120,
      "version": 0,
      "name": "LEBANON",
      "code": "LB"
    },
    {
      "id": 121,
      "version": 0,
      "name": "LESOTHO",
      "code": "LS"
    },
    {
      "id": 122,
      "version": 0,
      "name": "LIBERIA",
      "code": "LR"
    },
    {
      "id": 123,
      "version": 0,
      "name": "LIBYAN ARAB JAMAHIRIYA",
      "code": "LY"
    },
    {
      "id": 124,
      "version": 0,
      "name": "LIECHTENSTEIN",
      "code": "LI"
    },
    {
      "id": 125,
      "version": 0,
      "name": "LITHUANIA",
      "code": "LT"
    },
    {
      "id": 126,
      "version": 0,
      "name": "LUXEMBOURG",
      "code": "LU"
    },
    {
      "id": 127,
      "version": 0,
      "name": "MACAU",
      "code": "MO"
    },
    {
      "id": 128,
      "version": 0,
      "name": "MACEDONIA, THE FORMER YUGOSLAV REPUBLIC OF",
      "code": "MK"
    },
    {
      "id": 129,
      "version": 0,
      "name": "MADAGASCAR",
      "code": "MG"
    },
    {
      "id": 130,
      "version": 0,
      "name": "MALAWI",
      "code": "MW"
    },
    {
      "id": 131,
      "version": 0,
      "name": "MALAYSIA",
      "code": "MY"
    },
    {
      "id": 132,
      "version": 0,
      "name": "MALDIVES",
      "code": "MV"
    },
    {
      "id": 133,
      "version": 0,
      "name": "MALI",
      "code": "ML"
    },
    {
      "id": 134,
      "version": 0,
      "name": "MALTA",
      "code": "MT"
    },
    {
      "id": 135,
      "version": 0,
      "name": "MARSHALL ISLANDS",
      "code": "MH"
    },
    {
      "id": 136,
      "version": 0,
      "name": "MARTINIQUE",
      "code": "MQ"
    },
    {
      "id": 137,
      "version": 0,
      "name": "MAURITANIA",
      "code": "MR"
    },
    {
      "id": 138,
      "version": 0,
      "name": "MAURITIUS",
      "code": "MU"
    },
    {
      "id": 139,
      "version": 0,
      "name": "MAYOTTE",
      "code": "YT"
    },
    {
      "id": 140,
      "version": 0,
      "name": "MEXICO",
      "code": "MX"
    },
    {
      "id": 141,
      "version": 0,
      "name": "MICRONESIA, FEDERATED STATES OF",
      "code": "FM"
    },
    {
      "id": 142,
      "version": 0,
      "name": "MOLDOVA, REPUBLIC OF",
      "code": "MD"
    },
    {
      "id": 143,
      "version": 0,
      "name": "MONACO",
      "code": "MC"
    },
    {
      "id": 144,
      "version": 0,
      "name": "MONGOLIA",
      "code": "MN"
    },
    {
      "id": 145,
      "version": 0,
      "name": "MONTSERRAT",
      "code": "MS"
    },
    {
      "id": 146,
      "version": 0,
      "name": "MONTENEGRO",
      "code": "ME"
    },
    {
      "id": 147,
      "version": 0,
      "name": "MOROCCO",
      "code": "MA"
    },
    {
      "id": 148,
      "version": 0,
      "name": "MOZAMBIQUE",
      "code": "MZ"
    },
    {
      "id": 149,
      "version": 0,
      "name": "MYANMAR",
      "code": "MM"
    },
    {
      "id": 150,
      "version": 0,
      "name": "NAMIBIA",
      "code": "NA"
    },
    {
      "id": 151,
      "version": 0,
      "name": "NAURU",
      "code": "NR"
    },
    {
      "id": 152,
      "version": 0,
      "name": "NEPAL",
      "code": "NP"
    },
    {
      "id": 153,
      "version": 0,
      "name": "NETHERLANDS",
      "code": "NL"
    },
    {
      "id": 154,
      "version": 0,
      "name": "NETHERLANDS ANTILLES",
      "code": "AN"
    },
    {
      "id": 155,
      "version": 0,
      "name": "NEW CALEDONIA",
      "code": "NC"
    },
    {
      "id": 156,
      "version": 0,
      "name": "NEW ZEALAND",
      "code": "NZ"
    },
    {
      "id": 157,
      "version": 0,
      "name": "NICARAGUA",
      "code": "NI"
    },
    {
      "id": 158,
      "version": 0,
      "name": "NIGER",
      "code": "NE"
    },
    {
      "id": 159,
      "version": 0,
      "name": "NIGERIA",
      "code": "NG"
    },
    {
      "id": 160,
      "version": 0,
      "name": "NIUE",
      "code": "NU"
    },
    {
      "id": 161,
      "version": 0,
      "name": "NORFOLK ISLAND",
      "code": "NF"
    },
    {
      "id": 162,
      "version": 0,
      "name": "NORTHERN MARIANA ISLANDS",
      "code": "MP"
    },
    {
      "id": 163,
      "version": 0,
      "name": "NORWAY",
      "code": "NO"
    },
    {
      "id": 164,
      "version": 0,
      "name": "OMAN",
      "code": "OM"
    },
    {
      "id": 165,
      "version": 0,
      "name": "PAKISTAN",
      "code": "PK"
    },
    {
      "id": 166,
      "version": 0,
      "name": "PALAU",
      "code": "PW"
    },
    {
      "id": 167,
      "version": 0,
      "name": "PALESTINIAN TERRITORY, OCCUPIED",
      "code": "PS"
    },
    {
      "id": 168,
      "version": 0,
      "name": "PANAMA",
      "code": "PA"
    },
    {
      "id": 169,
      "version": 0,
      "name": "PAPUA NEW GUINEA",
      "code": "PG"
    },
    {
      "id": 170,
      "version": 0,
      "name": "PARAGUAY",
      "code": "PY"
    },
    {
      "id": 171,
      "version": 0,
      "name": "PERU",
      "code": "PE"
    },
    {
      "id": 172,
      "version": 0,
      "name": "PHILIPPINES",
      "code": "PH"
    },
    {
      "id": 173,
      "version": 0,
      "name": "PITCAIRN",
      "code": "PN"
    },
    {
      "id": 174,
      "version": 0,
      "name": "POLAND",
      "code": "PL"
    },
    {
      "id": 175,
      "version": 0,
      "name": "PORTUGAL",
      "code": "PT"
    },
    {
      "id": 176,
      "version": 0,
      "name": "PUERTO RICO",
      "code": "PR"
    },
    {
      "id": 177,
      "version": 0,
      "name": "QATAR",
      "code": "QA"
    },
    {
      "id": 178,
      "version": 0,
      "name": "REUNION",
      "code": "RE"
    },
    {
      "id": 179,
      "version": 0,
      "name": "ROMANIA",
      "code": "RO"
    },
    {
      "id": 180,
      "version": 0,
      "name": "RUSSIAN FEDERATION",
      "code": "RU"
    },
    {
      "id": 181,
      "version": 0,
      "name": "RWANDA",
      "code": "RW"
    },
    {
      "id": 182,
      "version": 0,
      "name": "SAINT HELENA",
      "code": "SH"
    },
    {
      "id": 183,
      "version": 0,
      "name": "SAINT KITTS AND NEVIS",
      "code": "KN"
    },
    {
      "id": 184,
      "version": 0,
      "name": "SAINT LUCIA",
      "code": "LC"
    },
    {
      "id": 185,
      "version": 0,
      "name": "SAINT PIERRE AND MIQUELON",
      "code": "PM"
    },
    {
      "id": 186,
      "version": 0,
      "name": "SAINT VINCENT AND THE GRENADINES",
      "code": "VC"
    },
    {
      "id": 187,
      "version": 0,
      "name": "SAMOA",
      "code": "WS"
    },
    {
      "id": 188,
      "version": 0,
      "name": "SAN MARINO",
      "code": "SM"
    },
    {
      "id": 189,
      "version": 0,
      "name": "SAO TOME AND PRINCIPE",
      "code": "ST"
    },
    {
      "id": 190,
      "version": 0,
      "name": "SAUDI ARABIA",
      "code": "SA"
    },
    {
      "id": 191,
      "version": 0,
      "name": "SENEGAL",
      "code": "SN"
    },
    {
      "id": 192,
      "version": 0,
      "name": "SERBIA",
      "code": "RS"
    },
    {
      "id": 193,
      "version": 0,
      "name": "SEYCHELLES",
      "code": "SC"
    },
    {
      "id": 194,
      "version": 0,
      "name": "SIERRA LEONE",
      "code": "SL"
    },
    {
      "id": 195,
      "version": 0,
      "name": "SINGAPORE",
      "code": "SG"
    },
    {
      "id": 196,
      "version": 0,
      "name": "SLOVAKIA",
      "code": "SK"
    },
    {
      "id": 197,
      "version": 0,
      "name": "SLOVENIA",
      "code": "SI"
    },
    {
      "id": 198,
      "version": 0,
      "name": "SOLOMON ISLANDS",
      "code": "SB"
    },
    {
      "id": 199,
      "version": 0,
      "name": "SOMALIA",
      "code": "SO"
    },
    {
      "id": 200,
      "version": 0,
      "name": "SOUTH AFRICA",
      "code": "ZA"
    },
    {
      "id": 201,
      "version": 0,
      "name": "SOUTH GEORGIA AND THE SOUTH SANDWICH ISLANDS",
      "code": "GS"
    },
    {
      "id": 202,
      "version": 0,
      "name": "SPAIN",
      "code": "ES"
    },
    {
      "id": 203,
      "version": 0,
      "name": "SRI LANKA",
      "code": "LK"
    },
    {
      "id": 204,
      "version": 0,
      "name": "SUDAN",
      "code": "SD"
    },
    {
      "id": 205,
      "version": 0,
      "name": "SURINAME,CREATION_TIME, LAST_UPDATE_TIME, VERSION",
      "code": "SR"
    },
    {
      "id": 206,
      "version": 0,
      "name": "SVALBARD AND JAN MAYEN",
      "code": "SJ"
    },
    {
      "id": 207,
      "version": 0,
      "name": "SWAZILAND",
      "code": "SZ"
    },
    {
      "id": 208,
      "version": 0,
      "name": "SWEDEN",
      "code": "SE"
    },
    {
      "id": 209,
      "version": 0,
      "name": "SWITZERLAND",
      "code": "CH"
    },
    {
      "id": 210,
      "version": 0,
      "name": "SYRIAN ARAB REPUBLIC",
      "code": "SY"
    },
    {
      "id": 211,
      "version": 0,
      "name": "TAIWAN, PROVINCE OF CHINA",
      "code": "TW"
    },
    {
      "id": 212,
      "version": 0,
      "name": "TAJIKISTAN",
      "code": "TJ"
    },
    {
      "id": 213,
      "version": 0,
      "name": "TANZANIA, UNITED REPUBLIC OF",
      "code": "TZ"
    },
    {
      "id": 214,
      "version": 0,
      "name": "THAILAND",
      "code": "TH"
    },
    {
      "id": 215,
      "version": 0,
      "name": "TOGO",
      "code": "TG"
    },
    {
      "id": 216,
      "version": 0,
      "name": "TOKELAU",
      "code": "TK"
    },
    {
      "id": 217,
      "version": 0,
      "name": "TONGA",
      "code": "TO"
    },
    {
      "id": 218,
      "version": 0,
      "name": "TRINIDAD AND TOBAGO",
      "code": "TT"
    },
    {
      "id": 219,
      "version": 0,
      "name": "TUNISIA",
      "code": "TN"
    },
    {
      "id": 220,
      "version": 0,
      "name": "TURKEY",
      "code": "TR"
    },
    {
      "id": 221,
      "version": 0,
      "name": "TURKMENISTAN",
      "code": "TM"
    },
    {
      "id": 222,
      "version": 0,
      "name": "TURKS AND CAICOS ISLANDS",
      "code": "TC"
    },
    {
      "id": 223,
      "version": 0,
      "name": "TUVALU",
      "code": "TV"
    },
    {
      "id": 224,
      "version": 0,
      "name": "UGANDA",
      "code": "UG"
    },
    {
      "id": 225,
      "version": 0,
      "name": "UKRAINE",
      "code": "UA"
    },
    {
      "id": 226,
      "version": 0,
      "name": "UNITED ARAB EMIRATES",
      "code": "AE"
    },
    {
      "id": 227,
      "version": 0,
      "name": "UNITED KINGDOM",
      "code": "GB"
    },
    {
      "id": 228,
      "version": 0,
      "name": "UNITED STATES",
      "code": "US"
    },
    {
      "id": 229,
      "version": 0,
      "name": "UNITED STATES MINOR OUTLYING ISLANDS",
      "code": "UM"
    },
    {
      "id": 230,
      "version": 0,
      "name": "URUGUAY",
      "code": "UY"
    },
    {
      "id": 231,
      "version": 0,
      "name": "UZBEKISTAN",
      "code": "UZ"
    },
    {
      "id": 232,
      "version": 0,
      "name": "VANUATU",
      "code": "VU"
    },
    {
      "id": 233,
      "version": 0,
      "name": "VENEZUELA",
      "code": "VE"
    },
    {
      "id": 234,
      "version": 0,
      "name": "VIET NAM",
      "code": "VN"
    },
    {
      "id": 235,
      "version": 0,
      "name": "VIRGIN ISLANDS, BRITISH",
      "code": "VG"
    },
    {
      "id": 236,
      "version": 0,
      "name": "VIRGIN ISLANDS, U.S.",
      "code": "VI"
    },
    {
      "id": 237,
      "version": 0,
      "name": "WALLIS AND FUTUNA",
      "code": "WF"
    },
    {
      "id": 238,
      "version": 0,
      "name": "WESTERN SAHARA",
      "code": "EH"
    },
    {
      "id": 239,
      "version": 0,
      "name": "YEMEN",
      "code": "YE"
    },
    {
      "id": 240,
      "version": 0,
      "name": "ZAMBIA",
      "code": "ZM"
    },
    {
      "id": 241,
      "version": 0,
      "name": "ZIMBABWE",
      "code": "ZW"
    }
  ]
}
